gcpdns.py
gcpdns-1.2.9.dist-info/LICENSE
gcpdns-1.2.9.dist-info/METADATA
gcpdns-1.2.9.dist-info/WHEEL
gcpdns-1.2.9.dist-info/entry_points.txt
gcpdns-1.2.9.dist-info/top_level.txt
gcpdns-1.2.9.dist-info/RECORD
