Metadata-Version: 2.1
Name: gcpdns
Version: 1.2.9
Summary: A Python module and CLI for managing zones and resource record sets on Google Cloud DNS
Home-page: https://domainaware.github.io/gcpdns
Author: Sean Whalen
Author-email: whalenster@gmail.com
License: Apache 2.0
Keywords: Google Cloud,GCP,DNS
Platform: UNKNOWN
Classifier: Development Status :: 5 - Production/Stable
Classifier: Intended Audience :: Developers
Classifier: Intended Audience :: Information Technology
Classifier: Operating System :: OS Independent
Classifier: License :: OSI Approved :: Apache Software License
Classifier: Programming Language :: Python :: 2
Classifier: Programming Language :: Python :: 2.7
Classifier: Programming Language :: Python :: 3
Classifier: Programming Language :: Python :: 3.0
Classifier: Programming Language :: Python :: 3.1
Classifier: Programming Language :: Python :: 3.2
Classifier: Programming Language :: Python :: 3.3
Classifier: Programming Language :: Python :: 3.4
Classifier: Programming Language :: Python :: 3.5
Classifier: Programming Language :: Python :: 3.6
Classifier: Programming Language :: Python :: 3.7
Requires-Dist: google-api-python-client
Requires-Dist: google-cloud
Requires-Dist: google-cloud-dns
Requires-Dist: publicsuffix2
Requires-Dist: click
